dash_extendable_graph/ExtendableGraph.py
dash_extendable_graph/__init__.py
dash_extendable_graph/_imports_.py
dash_extendable_graph/dash_extendable_graph.dev.js
dash_extendable_graph/dash_extendable_graph.min.js
dash_extendable_graph/metadata.json
dash_extendable_graph/package.json
dash_extendable_graph/plotly.min.js
dash_extendable_graph-1.3.0.dist-info/LICENSE
dash_extendable_graph-1.3.0.dist-info/METADATA
dash_extendable_graph-1.3.0.dist-info/WHEEL
dash_extendable_graph-1.3.0.dist-info/top_level.txt
dash_extendable_graph-1.3.0.dist-info/RECORD
