Metadata-Version: 2.1
Name: dash-extendable-graph
Version: 1.3.0
Summary: A Dash Graph component modified to support use of figure.data-structured input to extend and/or add traces.
Home-page: https://github.com/bcliang/dash-extendable-graph
Author: Brad Liang
Author-email: brad@bliang.com
License: MIT
Platform: UNKNOWN
Classifier: Programming Language :: Python :: 3
Classifier: Framework :: Dash
Classifier: Framework :: Flask
Classifier: Environment :: Web Environment
Classifier: License :: OSI Approved :: MIT License
Classifier: Topic :: Scientific/Engineering :: Visualization
